zimran/http_client/__init__.py
zimran/http_client/_async_http.py
zimran/http_client/_http.py
zimran_http-1.0.0.dist-info/METADATA
zimran_http-1.0.0.dist-info/WHEEL
zimran_http-1.0.0.dist-info/licenses/LICENSE
zimran_http-1.0.0.dist-info/RECORD
